lytrax_afm/__init__.py
lytrax_afm/__main__.py
lytrax_afm/_generation.py
lytrax_afm/_utils.py
lytrax_afm/_validation.py
lytrax_afm-1.0.1.dist-info/LICENSE
lytrax_afm-1.0.1.dist-info/METADATA
lytrax_afm-1.0.1.dist-info/WHEEL
lytrax_afm-1.0.1.dist-info/top_level.txt
lytrax_afm-1.0.1.dist-info/RECORD
