Metadata-Version: 2.1
Name: lytrax-afm
Version: 1.0.1
Summary: Greek AFM (TIN) Validator and Generator
Home-page: https://github.com/clytras/afm-python
Author: Christos Lytras
Author-email: christos.lytras@gmail.com
License: UNKNOWN
Platform: UNKNOWN
Classifier: Programming Language :: Python :: 3
Classifier: License :: OSI Approved :: MIT License
Classifier: Operating System :: OS Independent
Requires-Python: >=3.4
